pygifconverter/__init__.py
pygifconverter/converter.py
pygifconverter-1.0.2.dist-info/LICENSE
pygifconverter-1.0.2.dist-info/METADATA
pygifconverter-1.0.2.dist-info/WHEEL
pygifconverter-1.0.2.dist-info/top_level.txt
pygifconverter-1.0.2.dist-info/RECORD
